pytest_dogu_sdk/__init__.py
pytest_dogu_sdk/common.py
pytest_dogu_sdk/dogu.config.schema.json
pytest_dogu_sdk/dogu_config.py
pytest_dogu_sdk/dogu_hooks.py
pytest_dogu_sdk/dogu_sdk.py
pytest_dogu_sdk/remote_dest_report_client.py
pytest_dogu_sdk/remote_dest_reporter.py
pytest_dogu_sdk/routine_dest_report_client.py
pytest_dogu_sdk/routine_dest_reporter.py
pytest_dogu_sdk-1.1.1.dist-info/METADATA
pytest_dogu_sdk-1.1.1.dist-info/WHEEL
pytest_dogu_sdk-1.1.1.dist-info/RECORD
