Metadata-Version: 2.1
Name: pytest-dogu-sdk
Version: 1.1.1
Summary: pytest plugin for the Dogu
Author: Dogu Technologies
Requires-Python: >=3.9,<4.0
Classifier: Programming Language :: Python :: 3
Classifier: Programming Language :: Python :: 3.9
Classifier: Programming Language :: Python :: 3.10
Classifier: Programming Language :: Python :: 3.11
Classifier: Programming Language :: Python :: 3.12
Requires-Dist: dacite (==1.8.1)
Requires-Dist: jsonschema (==4.18.4)
Requires-Dist: requests (==2.31.0)
